package/__init__.py
package/missing_data.py
missing_data-1.0.0.dist-info/LICENSE.txt
missing_data-1.0.0.dist-info/METADATA
missing_data-1.0.0.dist-info/WHEEL
missing_data-1.0.0.dist-info/entry_points.txt
missing_data-1.0.0.dist-info/top_level.txt
missing_data-1.0.0.dist-info/RECORD
