Metadata-Version: 2.1
Name: missing-data
Version: 1.0.0
Summary: Missing Values
Home-page: UNKNOWN
Author: Tanay Agarwal
Author-email: tanaygupta1234@gmail.com
License: UNKNOWN
Platform: UNKNOWN
Classifier: Programming Language :: Python :: 3
Classifier: License :: OSI Approved :: MIT License
Classifier: Operating System :: OS Independent
Requires-Python: >=3.5
Requires-Dist: requests
